openpaygo/__init__.py
openpaygo/metrics_request.py
openpaygo/metrics_response.py
openpaygo/metrics_shared.py
openpaygo/token_decode.py
openpaygo/token_encode.py
openpaygo/token_shared.py
openpaygo/token_shared_extended.py
openpaygo-0.6.3.dist-info/licenses/LICENSE
test/test_encoder.py
utils/generate_test_tokens.py
openpaygo-0.6.3.dist-info/METADATA
openpaygo-0.6.3.dist-info/WHEEL
openpaygo-0.6.3.dist-info/top_level.txt
openpaygo-0.6.3.dist-info/RECORD
