Metadata-Version: 2.4
Name: openpaygo
Version: 0.6.3
Summary: OpenPAYGO Python library
Author-email: EnAccess <info@enaccess.org>
License-Expression: MIT
Project-URL: Homepage, https://enaccess.github.io/OpenPAYGO-docs/
Project-URL: Documentation, https://enaccess.github.io/OpenPAYGO-docs/
Project-URL: Repository, https://github.com/EnAccess/OpenPAYGO-python/
Project-URL: Issues, https://github.com/EnAccess/OpenPAYGO-python/issues
Project-URL: Changelog, https://github.com/EnAccess/OpenPAYGO-python/releases
Project-URL: Funding, https://github.com/sponsors/EnAccess
Keywords: paygo,open-paygo
Classifier: Development Status :: 5 - Production/Stable
Classifier: Intended Audience :: Developers
Classifier: Operating System :: Unix
Classifier: Operating System :: POSIX
Classifier: Operating System :: MacOS
Classifier: Operating System :: Microsoft :: Windows
Classifier: Programming Language :: Python
Classifier: Programming Language :: Python :: 3
Classifier: Programming Language :: Python :: 3.9
Classifier: Programming Language :: Python :: 3.10
Classifier: Programming Language :: Python :: 3.11
Classifier: Programming Language :: Python :: 3.12
Classifier: Programming Language :: Python :: 3.13
Classifier: Programming Language :: Python :: 3.14
Classifier: Programming Language :: Python :: 3.15
Classifier: Programming Language :: Python :: Implementation :: CPython
Classifier: Topic :: Utilities
Requires-Python: >=3.9
License-File: LICENSE
Requires-Dist: siphash>=0.0.1
Dynamic: license-file
